itchat/__init__.py
itchat/async_components/__init__.py
itchat/async_components/contact.py
itchat/async_components/hotreload.py
itchat/async_components/login.py
itchat/async_components/messages.py
itchat/async_components/register.py
itchat/components/__init__.py
itchat/components/contact.py
itchat/components/hotreload.py
itchat/components/login.py
itchat/components/messages.py
itchat/components/register.py
itchat/config.py
itchat/content.py
itchat/core.py
itchat/log.py
itchat/returnvalues.py
itchat/storage/__init__.py
itchat/storage/messagequeue.py
itchat/storage/templates.py
itchat/utils.py
itchat2_uos-1.0.0.dist-info/LICENSE
itchat2_uos-1.0.0.dist-info/WHEEL
itchat2_uos-1.0.0.dist-info/METADATA
itchat2_uos-1.0.0.dist-info/RECORD
